{
  "promotions": [
    {
      "title": "Primavera Urbana",
      "scope": "category",
      "status": "active",
      "discountType": "percent",
      "discountValue": 15,
      "category": "city",
      "description": "Sconto su bici da città selezionate: perfette per commuting e tempo libero.",
      "image": "/bici1.jpg",
      "images": [
        "/bici1.jpg"
      ],
      "endsAt": "2026-05-31",
      "showOnHome": true
    },
    {
      "title": "E-bike Trekking Weekend",
      "scope": "product",
      "status": "active",
      "discountType": "percent",
      "discountValue": 10,
      "productSku": "SKU-ELYSIUM-TREK-E50",
      "description": "Promo limitata sulla e-bike trekking: autonomia, comfort e assistenza premium.",
      "image": "/bici1.jpg",
      "images": [
        "/bici1.jpg"
      ],
      "endsAt": "2026-06-15",
      "showOnHome": true
    },
    {
      "title": "Kit Sicurezza",
      "scope": "general",
      "status": "active",
      "discountType": "amount",
      "discountValue": 20,
      "description": "€20 di sconto su accessori selezionati: luci, caschi e antifurti.",
      "image": "/bici1.jpg",
      "images": [
        "/bici1.jpg"
      ]
    },
    {
      "title": "Officina: Tagliando",
      "scope": "general",
      "status": "active",
      "discountType": "percent",
      "discountValue": 10,
      "description": "Sconto su check-up e manutenzione completa per ripartire in sicurezza.",
      "image": "/bici1.jpg",
      "images": [
        "/bici1.jpg"
      ]
    }
  ],
  "products": [
    {
      "name": "City Donna Classic 7V",
      "category": "city",
      "gender": "donna",
      "status": "available",
      "sku": "SKU-CITY-DONNA-7V",
      "slug": "city-donna-classic-7v",
      "price": "549",
      "description": "Bici da città comoda e affidabile, perfetta per spostamenti quotidiani.",
      "brand": "VincenzoBike",
      "image": "/bici1.jpg",
      "images": [
        "/bici1.jpg"
      ]
    },
    {
      "name": "MTB Trail Pro 29",
      "category": "mtb",
      "gender": "uomo",
      "status": "available",
      "sku": "SKU-MTB-TRAIL-29",
      "slug": "mtb-trail-pro-29",
      "price": "1290",
      "description": "Hardtail 29\" per trail e sterrati, assetto solido e componenti robusti.",
      "brand": "VincenzoBike",
      "image": "/bici1.jpg",
      "images": [
        "/bici1.jpg"
      ]
    },
    {
      "name": "Gravel Unisex Allroad",
      "category": "gravel",
      "gender": "unisex",
      "status": "available",
      "sku": "SKU-GRAVEL-ALLROAD",
      "slug": "gravel-unisex-allroad",
      "price": "1590",
      "description": "Versatile su asfalto e strade bianche: comfort, scorrevolezza e controllo.",
      "brand": "VincenzoBike",
      "image": "/bici1.jpg",
      "images": [
        "/bici1.jpg"
      ]
    },
    {
      "name": "Road Race 105",
      "category": "road",
      "gender": "uomo",
      "status": "preorder",
      "sku": "SKU-ROAD-RACE-105",
      "slug": "road-race-105",
      "price": "2190",
      "salePrice": "1990",
      "description": "Bici da corsa per allenamenti e granfondo: reattiva e precisa.",
      "brand": "VincenzoBike",
      "image": "/bici1.jpg",
      "images": [
        "/bici1.jpg"
      ]
    },
    {
      "name": "E-bike City Donna E35",
      "category": "ebike_city",
      "gender": "donna",
      "status": "available",
      "sku": "SKU-EBIKE-CITY-E35",
      "slug": "e-bike-city-donna-e35",
      "price": "2490",
      "description": "Assistita urbana: partenze fluide, comfort e autonomia reale per la settimana.",
      "brand": "VincenzoBike",
      "image": "/bici1.jpg",
      "images": [
        "/bici1.jpg"
      ],
      "ebike": {
        "batteryWh": 504,
        "rangeKm": 110,
        "motorW": 250,
        "torqueNm": 60,
        "chargeTimeH": 4.5,
        "display": "LCD",
        "assistLevels": 5
      }
    },
    {
      "name": "E-bike Trekking Unisex E50",
      "category": "ebike_trekking",
      "gender": "unisex",
      "status": "available",
      "sku": "SKU-ELYSIUM-TREK-E50",
      "slug": "e-bike-trekking-unisex-e50",
      "price": "3290",
      "description": "Trekking assistita: autonomia estesa, portapacchi e comfort per viaggi e commuting.",
      "brand": "VincenzoBike",
      "image": "/bici1.jpg",
      "images": [
        "/bici1.jpg"
      ],
      "ebike": {
        "batteryWh": 630,
        "rangeKm": 130,
        "motorW": 250,
        "torqueNm": 75,
        "chargeTimeH": 5.5,
        "display": "Color",
        "assistLevels": 5
      }
    },
    {
      "name": "E-MTB Enduro E70",
      "category": "ebike_emtb",
      "gender": "uomo",
      "status": "available",
      "sku": "SKU-EMTB-ENDURO-E70",
      "slug": "e-mtb-enduro-e70",
      "price": "4490",
      "description": "E-MTB pronta per il trail: coppia generosa e controllo in discesa.",
      "brand": "VincenzoBike",
      "image": "/bici1.jpg",
      "images": [
        "/bici1.jpg"
      ],
      "ebike": {
        "batteryWh": 720,
        "rangeKm": 120,
        "motorW": 250,
        "torqueNm": 85,
        "chargeTimeH": 6,
        "display": "Color",
        "assistLevels": 5
      }
    },
    {
      "name": "Casco Urban MIPS",
      "category": "accessory",
      "gender": "unisex",
      "status": "available",
      "sku": "SKU-ACC-CASCO-MIPS",
      "slug": "casco-urban-mips",
      "price": "79",
      "description": "Casco urbano leggero con protezione MIPS e ventilazione ottimizzata.",
      "brand": "VincenzoBike",
      "image": "/bici1.jpg",
      "images": [
        "/bici1.jpg"
      ]
    },
    {
      "name": "Catena 11v Rinforzata",
      "category": "spare_part",
      "status": "available",
      "sku": "SKU-RIC-CATENA-11V",
      "slug": "catena-11v-rinforzata",
      "price": "29",
      "description": "Catena 11 velocità per trasmissioni strada/gravel: scorrevolezza e durata.",
      "brand": "VincenzoBike",
      "image": "/bici1.jpg",
      "images": [
        "/bici1.jpg"
      ]
    }
  ],
  "brand": {
    "name": "VincenzoBike",
    "headline": "VincenzoBike",
    "subheadline": "Assistenza, manutenzione e riparazioni per bici muscolari, elettriche e a pedalata assistita. Interventi a domicilio su richiesta. In officina trovi pompa gratuita per il gonfiaggio e un angolo shop con accessori, ricambi e gadget, con possibilità di ordinare componenti specifici."
  },
  "kpis": [
    {
      "label": "Bici",
      "value": "Muscolari · E-bike · Assistite"
    },
    {
      "label": "A domicilio",
      "value": "Su richiesta"
    },
    {
      "label": "Pompa",
      "value": "Gratis"
    }
  ],
  "services": [
    {
      "id": "manutenzione",
      "category": "Officina",
      "title": "Manutenzione completa",
      "desc": "Check-up, regolazioni e messa a punto per tornare a pedalare in sicurezza.",
      "bullets": [
        "Freni",
        "Cambio",
        "Trasmissione"
      ],
      "image": "https://upload.wikimedia.org/wikipedia/commons/4/4c/Workbench_of_a_bicycle_dealer.jpg"
    },
    {
      "id": "riparazioni",
      "category": "Riparazioni",
      "title": "Riparazioni rapide",
      "desc": "Interventi su forature, ruote, freni e componenti: dalla diagnosi alla soluzione.",
      "bullets": [
        "Forature",
        "Ruote",
        "Freni"
      ],
      "image": "https://upload.wikimedia.org/wikipedia/commons/9/97/Bicycle_repair_shop_-_bike_parts_on_work_bench.jpg"
    },
    {
      "id": "ebike",
      "category": "E-bike",
      "title": "Elettriche e assistite",
      "desc": "Assistenza e manutenzione su bici elettriche e a pedalata assistita, con controlli mirati.",
      "bullets": [
        "Diagnosi",
        "Check componenti",
        "Messa a punto"
      ],
      "image": "/1.png"
    },
    {
      "id": "ricambi",
      "category": "Shop",
      "title": "Accessori e ricambi",
      "desc": "Vendita accessori, ricambi e gadget. Possibilità di ordinare ricambistica specifica per ogni necessità.",
      "bullets": [
        "Accessori",
        "Ricambi",
        "Ordini"
      ],
      "image": "/2.png"
    }
  ],
  "models": [
    {
      "id": "urban",
      "name": "Urban Pulse",
      "category": "City / Commuting",
      "price": "€3.490",
      "rangeKm": 150,
      "topSpeed": "25 km/h",
      "image": "/bici1.jpg"
    },
    {
      "id": "mountain",
      "name": "Mountain Vector",
      "category": "Trail / Enduro",
      "price": "€4.990",
      "rangeKm": 130,
      "topSpeed": "25 km/h",
      "image": "/bici1.jpg"
    },
    {
      "id": "cargo",
      "name": "Cargo Atlas",
      "category": "Family / Delivery",
      "price": "€4.290",
      "rangeKm": 120,
      "topSpeed": "25 km/h",
      "image": "/bici1.jpg"
    },
    {
      "id": "folding",
      "name": "Folding Neo",
      "category": "Compact / Travel",
      "price": "€2.990",
      "rangeKm": 110,
      "topSpeed": "25 km/h",
      "image": "/bici1.jpg"
    }
  ],
  "features": [
    {
      "title": "Manutenzione e check-up",
      "desc": "Controlli e regolazioni per una bici sicura e scorrevole: freni, cambio, trasmissione e serraggi."
    },
    {
      "title": "Riparazioni in officina",
      "desc": "Interventi su forature, ruote, freni e componenti: dalla diagnosi alla soluzione."
    },
    {
      "title": "Bici elettriche e assistite",
      "desc": "Assistenza e manutenzione su e-bike e pedalata assistita, con controlli mirati."
    },
    {
      "title": "Riparazioni a domicilio",
      "desc": "Disponibile su richiesta, in base al tipo di intervento e disponibilità."
    },
    {
      "title": "Pompa gratuita",
      "desc": "Pompa per gonfiaggio ruote disponibile gratuitamente in officina."
    },
    {
      "title": "Accessori e ricambi",
      "desc": "Vendita accessori, ricambi e gadget, con possibilità di ordinare ricambistica specifica."
    }
  ],
  "technology": [
    {
      "title": "Diagnosi e regolazioni",
      "desc": "Controlli mirati e regolazioni per componenti e trasmissione, con attenzione alla sicurezza.",
      "image": "/3.png"
    },
    {
      "title": "Ruote e pneumatici",
      "desc": "Interventi su forature, camere d’aria e gomme: gonfiaggio e controlli disponibili anche in officina.",
      "image": "/4.png"
    },
    {
      "title": "Ricambi su ordinazione",
      "desc": "Possibilità di ordinare ricambistica specifica per ogni necessità, oltre ad accessori e gadget.",
      "image": "/5.png"
    }
  ],
  "gallery": [
    "https://upload.wikimedia.org/wikipedia/commons/2/29/Bike_workshop_-_bicycle_repair_shop.jpg",
    "https://upload.wikimedia.org/wikipedia/commons/d/d7/Munich_-_Two_men_working_in_a_Bicycle_repair_shop_-_5893.jpg",
    "https://upload.wikimedia.org/wikipedia/commons/9/97/Bicycle_repair_shop_-_bike_parts_on_work_bench.jpg",
    "https://upload.wikimedia.org/wikipedia/commons/4/4c/Workbench_of_a_bicycle_dealer.jpg",
    "https://upload.wikimedia.org/wikipedia/commons/9/91/Bicycle_repair_shop.jpg",
    "https://upload.wikimedia.org/wikipedia/commons/0/0f/Le_m%C3%A9cano-v%C3%A9los.jpg"
  ],
  "testimonials": [
    {
      "name": "Marco S.",
      "role": "City rider · Marcianise",
      "quote": "Check-up super accurato e bici tornata perfetta. Mi hanno sistemato freni e cambio in tempi rapidi.",
      "rating": 5
    },
    {
      "name": "Giulia P.",
      "role": "E-bike · Caserta",
      "quote": "Ottima assistenza sulla mia pedalata assistita: diagnosi chiara e intervento risolutivo. Consigliatissimi.",
      "rating": 5
    },
    {
      "name": "Antonio R.",
      "role": "Riparazione a domicilio",
      "quote": "Servizio a domicilio comodissimo: mi hanno risolto il problema senza dover spostare la bici.",
      "rating": 5
    }
  ],
  "workshop": {
    "title": "Officina / Per ogni necessità",
    "subtitle": "Manutenzione ordinaria, interventi tecnici e ricambi selezionati. Un servizio pulito, credibile e coerente con un brand premium.",
    "cards": [
      {
        "title": "Manutenzione",
        "desc": "Tagliando, check-up, controlli periodici: performance e sicurezza sempre al top.",
        "image": "https://source.unsplash.com/1600x1200/?motorcycle,maintenance,garage&sig=21",
        "objectPositionMobile": "55% 45%",
        "objectPositionDesktop": "55% 40%"
      },
      {
        "title": "Riparazioni",
        "desc": "Tecnici al lavoro, interventi mirati e componenti verificati: riparti subito, senza compromessi.",
        "image": "https://source.unsplash.com/1600x1200/?motorcycle,mechanic,repair&sig=22",
        "objectPositionMobile": "50% 50%",
        "objectPositionDesktop": "50% 45%"
      },
      {
        "title": "Ricambi",
        "desc": "Componenti, trasmissione, freni, accessori: dettagli tecnici e compatibilità garantita.",
        "image": "https://source.unsplash.com/1600x1200/?motorcycle,parts,engine&sig=23",
        "objectPositionMobile": "50% 55%",
        "objectPositionDesktop": "50% 50%"
      },
      {
        "title": "Diagnostica",
        "desc": "Diagnostica e set-up: lettura parametri, test, calibrazioni e interventi mirati su elettronica e componenti.",
        "image": "https://source.unsplash.com/1600x1200/?motorcycle,diagnostic,tools&sig=24",
        "objectPositionMobile": "50% 50%",
        "objectPositionDesktop": "50% 45%"
      },
      {
        "title": "Assistenza",
        "desc": "Supporto, consulenza e servizi dedicati: dalla scelta al post-vendita.",
        "image": "https://source.unsplash.com/1600x1200/?motorcycle,service,technician&sig=25",
        "objectPositionMobile": "50% 45%",
        "objectPositionDesktop": "55% 45%"
      }
    ]
  },
  "footer": {
    "email": "info@vincenzobike.example",
    "phone": "+39 000 000 0000",
    "address": "Via Novelli, 51, Marcianise (CE) 81025, Italia",
    "social": [
      {
        "label": "Instagram",
        "href": "#"
      },
      {
        "label": "YouTube",
        "href": "#"
      },
      {
        "label": "X",
        "href": "#"
      }
    ]
  }
}
